Accounts/__init__.py
Accounts/settings.py
Accounts/urls.py
Accounts/wsgi.py
AccountsApp/__init__.py
AccountsApp/admin.py
AccountsApp/api.py
AccountsApp/apps.py
AccountsApp/models.py
AccountsApp/tests.py
AccountsApp/urls.py
AccountsApp/views.py
AccountsApp/migrations/0001_initial.py
AccountsApp/migrations/__init__.py
AccountsApp/utils/__init__.py
AccountsApp/utils/blockchain_interface.py
AccountsApp/utils/code_generator.py
AccountsApp/utils/decorators.py
AccountsApp/utils/shortcuts.py
uzu_accounts_app-1.0.dist-info/LICENSE.txt
uzu_accounts_app-1.0.dist-info/METADATA
uzu_accounts_app-1.0.dist-info/WHEEL
uzu_accounts_app-1.0.dist-info/top_level.txt
uzu_accounts_app-1.0.dist-info/RECORD
